MANIFEST.in
README.rst
setup.py
hejtado/__init__.py
hejtado/quido/__init__.py
hejtado/quido/app.py
hejtado/quido/business.py
hejtado/quido/logging.conf
hejtado/quido/settings.py
hejtado/quido/api/__init__.py
hejtado/quido/api/endpoints/__init__.py
hejtado/quido/api/endpoints/relays.py
hejtado/quido/api/endpoints/thermometers.py
hejtado_quido.egg-info/PKG-INFO
hejtado_quido.egg-info/SOURCES.txt
hejtado_quido.egg-info/dependency_links.txt
hejtado_quido.egg-info/entry_points.txt
hejtado_quido.egg-info/requires.txt
hejtado_quido.egg-info/top_level.txt