Metadata-Version: 2.1
Name: hejtado-quido
Version: 0.2.6
Summary: Thermometer Quido RESTful API based on Flask and Flask-RESTPlus
Home-page: https://github.com/hejtado/quido
Author: Lumir Jasiok
License: UNKNOWN
Keywords: rest restful api flask swagger openapi flask-restplus
Platform: UNKNOWN
Classifier: Development Status :: 4 - Beta
Classifier: Intended Audience :: Developers
Classifier: Topic :: Software Development :: Libraries :: Application Frameworks
Classifier: License :: OSI Approved :: GNU General Public License v3 (GPLv3)
Classifier: Programming Language :: Python :: 2
Classifier: Programming Language :: Python :: 2.7
Classifier: Programming Language :: Python :: 3
Classifier: Programming Language :: Python :: 3.5
Classifier: Programming Language :: Python :: 3.6
Classifier: Programming Language :: Python :: 3.7
